Eikthyr/__init__.py
Eikthyr/cache.py
Eikthyr/cmd.py
Eikthyr/data.py
Eikthyr/envcheck.py
Eikthyr/logging.py
Eikthyr/param.py
Eikthyr/run.py
Eikthyr/specialtask.py
Eikthyr/task.py
Eikthyr-0.4.2.dist-info/LICENSE
Eikthyr-0.4.2.dist-info/METADATA
Eikthyr-0.4.2.dist-info/WHEEL
Eikthyr-0.4.2.dist-info/top_level.txt
Eikthyr-0.4.2.dist-info/RECORD
